mockamorph/__init__.py
mockamorph/__version__.py
mockamorph/_core.py
mockamorph/py.typed
mockamorph-0.4.0.dist-info/METADATA
mockamorph-0.4.0.dist-info/WHEEL
mockamorph-0.4.0.dist-info/licenses/LICENSE
mockamorph-0.4.0.dist-info/RECORD
