Metadata-Version: 2.4
Name: mockamorph
Version: 0.4.0
Summary: Lightweight interface mocking library for Python for expectation-driven testing
Project-URL: Homepage, https://github.com/dartt0n/mockamorph
Project-URL: Documentation, https://github.com/dartt0n/mockamorph#readme
Project-URL: Repository, https://github.com/dartt0n/mockamorph
Project-URL: Issues, https://github.com/dartt0n/mockamorph/issues
Author: Anton Kudryavtsev
License-Expression: MIT
License-File: LICENSE
Keywords: mock,mocking,pytest,testing,unittest
Classifier: Development Status :: 4 - Beta
Classifier: Intended Audience :: Developers
Classifier: License :: OSI Approved :: MIT License
Classifier: Operating System :: OS Independent
Classifier: Programming Language :: Python :: 3
Classifier: Programming Language :: Python :: 3.12
Classifier: Programming Language :: Python :: 3.13
Classifier: Topic :: Software Development :: Testing
Classifier: Topic :: Software Development :: Testing :: Mocking
Requires-Python: >=3.12
